adfpy/__init__.py
adfpy/activities/__init__.py
adfpy/activities/control.py
adfpy/activities/execution.py
adfpy/activity.py
adfpy/deploy.py
adfpy/error.py
adfpy/pipeline.py
adfpy/trigger.py
adfpy-0.1.0.dist-info/entry_points.txt
adfpy-0.1.0.dist-info/WHEEL
adfpy-0.1.0.dist-info/METADATA
adfpy-0.1.0.dist-info/RECORD
